notion/__init__.py
notion/client.py
notion/errors.py
notion/format.py
notion_python-1.0.2.dist-info/DESCRIPTION.rst
notion_python-1.0.2.dist-info/METADATA
notion_python-1.0.2.dist-info/RECORD
notion_python-1.0.2.dist-info/WHEEL
notion_python-1.0.2.dist-info/metadata.json
notion_python-1.0.2.dist-info/top_level.txt
tests/__init__.py
tests/client_test.py
tests/format_test.py
