Metadata-Version: 2.0
Name: notion-python
Version: 1.0.2
Summary: API Client for Notion
Home-page: UNKNOWN
Author: UNKNOWN
Author-email: UNKNOWN
License: UNKNOWN
Project-URL: Source, https://github.com/notion-data/notion-python
Keywords: notion api client
Platform: UNKNOWN
Classifier: Programming Language :: Python :: 2.7
Classifier: Programming Language :: Python :: 3.4
Requires-Dist: requests
